setup.py
minifail/__init__.py
minifail/getifaddrs.py
minifail/main.py
minifail/netutils.py
minifail/notifier.py
minifail.egg-info/PKG-INFO
minifail.egg-info/SOURCES.txt
minifail.egg-info/dependency_links.txt
minifail.egg-info/entry_points.txt
minifail.egg-info/requires.txt
minifail.egg-info/top_level.txt