Metadata-Version: 1.0
Name: minifail
Version: 0.1.1
Summary: minifail is a simple IP failover compatible with Linux/BSD/MacOS
Home-page: https://github.com/gautier/minifail
Author: Gautier Hayoun
Author-email: ghayoun@gmail.com
License: MIT
Platform: UNKNOWN
